README.md
perk_mdplib.py
setup.cfg
setup.py
perk_mdplib.egg-info/PKG-INFO
perk_mdplib.egg-info/SOURCES.txt
perk_mdplib.egg-info/dependency_links.txt
perk_mdplib.egg-info/top_level.txt