Metadata-Version: 1.2
Name: perk-mdplib
Version: 1.24.2
Summary: A powerful package that provide some interesting function
Home-page: https://grigoprg.webnode.it
Author: Marco Della Putta
Author-email: marcodp183@gmail.com
Maintainer: Marco Della Putta
Maintainer-email: marcodp183@gmail.com
License: GNU License
Platform: UNKNOWN
